vibe_logger/__init__.py
vibe_colored_logger-0.1.7.dist-info/METADATA
vibe_colored_logger-0.1.7.dist-info/WHEEL
vibe_colored_logger-0.1.7.dist-info/top_level.txt
vibe_colored_logger-0.1.7.dist-info/RECORD
