Metadata-Version: 2.4
Name: vibe-colored-logger
Version: 0.1.7
Summary: A colored logger with context injection support for Python applications.
Author-email: Your Name <your.email@example.com>
License: MIT
Classifier: Programming Language :: Python :: 3
Classifier: License :: OSI Approved :: MIT License
Classifier: Operating System :: OS Independent
Requires-Python: >=3.7
Requires-Dist: coloredlogs>=15.0.1
